{
  "ComponentIndexes": {
    "Component1": 9
  },
  "ControlUniqueGuids": {},
  "ControlUniqueIds": {
    "6f4a661c-b0b9-47c7-850e-056aa27a82ca": 226,
    "a99308fb-2b04-457c-bb7c-9f87f1f945b0": 225,
    "AddButton": 95,
    "App": 1,
    "Button2": 110,
    "Button3": 88,
    "Button4_1": 47,
    "Button4_2": 158,
    "Button4_3": 22,
    "Button4_4": 48,
    "cancelButton": 85,
    "Circle1": 86,
    "Component1": 3,
    "DataCardKey14_2": 219,
    "DataCardKey15_2": 179,
    "DataCardKey16_2": 194,
    "DataCardKey17_2": 199,
    "DataCardKey18_2": 204,
    "DataCardKey19_2": 209,
    "DataCardKey20_2": 214,
    "DataCardKey22_2": 174,
    "DataCardKey3_2": 184,
    "DataCardKey5_2": 189,
    "DataCardValue14_2": 220,
    "DataCardValue15_2": 180,
    "DataCardValue16_2": 195,
    "DataCardValue17_2": 200,
    "DataCardValue18_2": 205,
    "DataCardValue19_2": 210,
    "DataCardValue20_2": 215,
    "DataCardValue22_2": 175,
    "DataCardValue3_2": 185,
    "DataCardValue5_2": 190,
    "date_dropdown": 102,
    "date_label": 128,
    "date_val": 142,
    "del_v": 94,
    "delete_icon": 81,
    "deleteButton": 84,
    "DoneButton": 170,
    "Dropdown1": 165,
    "Dropdown2": 167,
    "Dropdown3": 169,
    "Edit_container": 93,
    "EditSuccess_screen": 18,
    "error_label": 109,
    "ErrorMessage14_2": 221,
    "ErrorMessage15_2": 181,
    "ErrorMessage16_2": 196,
    "ErrorMessage17_2": 201,
    "ErrorMessage18_2": 206,
    "ErrorMessage19_2": 211,
    "ErrorMessage20_2": 216,
    "ErrorMessage21_2": 176,
    "ErrorMessage3_2": 186,
    "ErrorMessage5_2": 191,
    "eval1_label": 130,
    "eval1_val": 144,
    "eval2_label": 131,
    "eval2_val": 145,
    "eval3_label": 132,
    "eval3_val": 146,
    "eval4_label": 133,
    "eval4_val": 147,
    "eval5_label": 134,
    "eval5_val": 148,
    "eval6_label": 135,
    "eval6_val": 149,
    "evaluation_1_DataCard2_2": 177,
    "evaluation_2_DataCard2_2": 192,
    "evaluation_3_DataCard2_2": 197,
    "evaluation_4_DataCard2_2": 202,
    "evaluation_5_DataCard2_2": 207,
    "evaluation_6_DataCard2_2": 212,
    "feedback_DataCard2_2": 217,
    "Form": 171,
    "Form1": 59,
    "gal_group": 151,
    "Gallery2": 72,
    "Gallery2_1": 77,
    "Gallery4": 24,
    "Gallery5": 27,
    "galleryTemplate1": 138,
    "galleryTemplate3": 73,
    "galleryTemplate3_1": 78,
    "galleryTemplate5": 25,
    "galleryTemplate6": 28,
    "grader_1": 37,
    "grader_2": 38,
    "grader_3": 238,
    "grader_4": 239,
    "grader_dropdown": 107,
    "Grader_dropdown_2": 121,
    "grader_label": 126,
    "Grader_login_button": 11,
    "Grader_MainContainer": 91,
    "grader_val": 140,
    "GraderCard_name": 63,
    "Grading_screen": 159,
    "GradingCertification_screen": 96,
    "group_1": 36,
    "group_dropdown": 105,
    "Group_dropdown_1": 120,
    "group_id_DataCard3_2": 172,
    "group_label": 125,
    "Group_MainContainer": 90,
    "group_val": 139,
    "Group4": 7,
    "GroupCard_name": 60,
    "gs_grader_label": 166,
    "gs_group_label": 164,
    "gs_infoDropdowns": 224,
    "gs_infoLabels": 222,
    "gs_venue_label": 168,
    "Icon1": 45,
    "Icon1_1": 163,
    "Icon1_10": 98,
    "Icon1_11": 161,
    "Icon1_12": 235,
    "Icon1_2": 6,
    "Icon1_3": 57,
    "Icon1_4": 100,
    "Icon1_5": 43,
    "Icon1_6": 116,
    "Icon1_7": 233,
    "Icon1_8": 55,
    "Icon1_9": 114,
    "Icon2": 76,
    "Icon4": 75,
    "Icon4_1": 80,
    "Icon5": 58,
    "Icon6": 82,
    "Icon8": 87,
    "iconCheck1": 156,
    "iconCheck1_1": 20,
    "iconCircle1": 155,
    "iconCircle1_1": 19,
    "lab_group": 152,
    "Label1": 4,
    "Label10": 68,
    "Label10_1": 69,
    "Label11": 101,
    "Label11_1": 103,
    "Label11_2": 106,
    "Label11_3": 108,
    "Label13": 54,
    "Label14": 83,
    "Label15": 26,
    "Label2": 29,
    "Label2_1": 30,
    "Label2_2": 240,
    "Label2_3": 32,
    "Label2_4": 241,
    "Label2_5": 242,
    "Label3": 44,
    "Label3_1": 10,
    "Label3_2": 115,
    "Label3_3": 99,
    "Label3_4": 162,
    "Label3_5": 56,
    "Label3_6": 234,
    "Label4": 5,
    "Label5": 74,
    "Label5_1": 79,
    "Label6": 118,
    "Label7": 119,
    "Label8": 67,
    "Label8_1": 71,
    "Label9": 61,
    "Label9_1": 64,
    "LblSuccessMsg1": 157,
    "LblSuccessMsg1_1": 21,
    "List_gallery": 137,
    "List_screen": 112,
    "Login_screen": 8,
    "Management_Screen": 50,
    "Manager_login_button": 15,
    "Modeselect_screen": 41,
    "NewSuccess_screen": 154,
    "next_arrow": 14,
    "password_button": 13,
    "password_group": 16,
    "password_textInput": 12,
    "Rectangle1": 117,
    "Rectangle3": 42,
    "Rectangle3_1": 9,
    "Rectangle3_2": 113,
    "Rectangle3_3": 97,
    "Rectangle3_4": 160,
    "Rectangle3_5": 51,
    "Rectangle3_6": 232,
    "Rectangle5": 66,
    "Rectangle6": 53,
    "Rectangle7": 52,
    "Rectangle8": 70,
    "room_dropdown": 104,
    "room_label": 129,
    "room_val": 143,
    "ScoreSummaryTable": 23,
    "SideBar_container": 92,
    "Sort_dropdown_1": 123,
    "Sort_dropdown_2": 124,
    "StarVisible14_2": 218,
    "StarVisible15_2": 178,
    "StarVisible16_2": 193,
    "StarVisible17_2": 198,
    "StarVisible18_2": 203,
    "StarVisible19_2": 208,
    "StarVisible20_2": 213,
    "StarVisible21_2": 173,
    "StarVisible3_2": 183,
    "StarVisible5_2": 188,
    "tab_group": 49,
    "tab_group_1": 17,
    "tab_group_2": 153,
    "tab_group_3": 111,
    "tab_group_4": 223,
    "tab_group_5": 89,
    "tab_group_6": 236,
    "Test_7F478737223C4B69": 2,
    "TextInput10": 62,
    "TextInput10_1": 65,
    "toListScreen_button": 46,
    "total_1": 39,
    "total_2": 40,
    "total_label": 136,
    "total_val": 150,
    "user_id_DataCard1_2": 182,
    "vanue_label": 127,
    "vanue_val": 141,
    "Venue_dropdown_3": 122,
    "Venue_dropdown_4": 33,
    "venue_id_DataCard1_2": 187
  },
  "DoesTestStepsMetadataExist": true,
  "FunctionParamsInvariantScripts": {},
  "FunctionParamsInvariantScriptsOnInstances": {},
  "HeaderLastSavedDateTimeUTC": "03/07/2023 21:21:27",
  "IsLegacyComponentAllowGlobalScopeCase": false,
  "LocalConnectionIDReferences": {
    "d6d87367-50af-44df-bd8a-509b1596d09d": "\"/providers/microsoft.powerapps/apis/shared_sharepointonline/connections/09fda4ea79c44b7c8973c7bce7a66632\""
  },
  "LocalDatabaseReferencesAsEmpty": false,
  "LocalResourceFileNames": {},
  "LocalResourceRootPaths": {},
  "OrderComponentMetadata": {
    "b865ef078df94062b671e7e610e0cb05": 0
  },
  "OrderComponentTemplate": {
    "b865ef078df94062b671e7e610e0cb05": 0
  },
  "OrderDataSource": {
    "CustomGallerySample": 0,
    "DropDownSample": 1,
    "eval_col": 6,
    "grader_col": 8,
    "Grading_table": 2,
    "group_col": 9,
    "Group_table": 3,
    "User_table": 4,
    "venue_col": 7,
    "Venue_table": 5
  },
  "OrderGroupControls": {
    "AddButton": {
      "Circle1": 1,
      "Icon8": 0
    },
    "del_v": {
      "cancelButton": 0,
      "deleteButton": 1,
      "Icon6": 3,
      "Label14": 2,
      "Rectangle8": 4
    },
    "Edit_container": {
      "Button3": 0,
      "Form1": 2,
      "Icon5": 3,
      "Label13": 1,
      "Rectangle6": 4
    },
    "gal_group": {
      "date_val": 3,
      "eval1_val": 5,
      "eval2_val": 6,
      "eval3_val": 7,
      "eval4_val": 8,
      "eval5_val": 9,
      "eval6_val": 10,
      "grader_val": 1,
      "group_val": 0,
      "room_val": 4,
      "total_val": 11,
      "vanue_val": 2
    },
    "Grader_MainContainer": {
      "Gallery2_1": 1,
      "Label10_1": 0
    },
    "Group_MainContainer": {
      "Gallery2": 1,
      "Label10": 0
    },
    "Group4": {
      "Icon1_2": 1,
      "Label1": 0,
      "Label4": 2
    },
    "gs_infoDropdowns": {
      "Dropdown1": 1,
      "Dropdown2": 2,
      "Dropdown3": 0
    },
    "gs_infoLabels": {
      "gs_grader_label": 1,
      "gs_group_label": 0,
      "gs_venue_label": 2
    },
    "lab_group": {
      "date_label": 3,
      "eval1_label": 5,
      "eval2_label": 6,
      "eval3_label": 7,
      "eval4_label": 8,
      "eval5_label": 9,
      "eval6_label": 10,
      "grader_label": 1,
      "group_label": 0,
      "room_label": 4,
      "total_label": 11,
      "vanue_label": 2
    },
    "password_group": {
      "next_arrow": 2,
      "password_button": 0,
      "password_textInput": 1
    },
    "SideBar_container": {
      "Label8": 1,
      "Label8_1": 2,
      "Rectangle5": 0
    },
    "tab_group": {
      "Icon1": 1,
      "Icon1_5": 3,
      "Label3": 2,
      "Rectangle3": 0
    },
    "tab_group_1": {
      "Label3_1": 1,
      "Rectangle3_1": 0
    },
    "tab_group_2": {
      "Icon1_6": 1,
      "Icon1_9": 3,
      "Label3_2": 2,
      "Rectangle3_2": 0
    },
    "tab_group_3": {
      "Icon1_10": 3,
      "Icon1_4": 1,
      "Label3_3": 2,
      "Rectangle3_3": 0
    },
    "tab_group_4": {
      "Icon1_1": 1,
      "Icon1_11": 3,
      "Label3_4": 2,
      "Rectangle3_4": 0
    },
    "tab_group_5": {
      "Icon1_3": 1,
      "Icon1_8": 3,
      "Label3_5": 2,
      "Rectangle3_5": 0
    },
    "tab_group_6": {
      "Icon1_12": 3,
      "Icon1_7": 1,
      "Label3_6": 2,
      "Rectangle3_6": 0
    }
  },
  "OrderPcfTemplate": {},
  "OrderTemplate": {},
  "OrderXMLTemplate": {
    "button": 2,
    "circle": 5,
    "dropdown": 7,
    "form": 8,
    "gallery": 6,
    "icon": 4,
    "label": 1,
    "rectangle": 0,
    "text": 3
  },
  "OverridablePropertiesEntry": {
    "6f4a661c-b0b9-47c7-850e-056aa27a82ca": {},
    "a99308fb-2b04-457c-bb7c-9f87f1f945b0": {},
    "AddButton": {},
    "App": {},
    "Button2": {},
    "Button3": {},
    "Button4_1": {},
    "Button4_2": {},
    "Button4_3": {},
    "Button4_4": {},
    "cancelButton": {},
    "Circle1": {},
    "Component1": {},
    "DataCardKey14_2": {},
    "DataCardKey15_2": {},
    "DataCardKey16_2": {},
    "DataCardKey17_2": {},
    "DataCardKey18_2": {},
    "DataCardKey19_2": {},
    "DataCardKey20_2": {},
    "DataCardKey22_2": {},
    "DataCardKey3_2": {},
    "DataCardKey5_2": {},
    "DataCardValue14_2": {},
    "DataCardValue15_2": {},
    "DataCardValue16_2": {},
    "DataCardValue17_2": {},
    "DataCardValue18_2": {},
    "DataCardValue19_2": {},
    "DataCardValue20_2": {},
    "DataCardValue22_2": {},
    "DataCardValue3_2": {},
    "DataCardValue5_2": {},
    "date_dropdown": {},
    "date_label": {},
    "date_val": {},
    "del_v": {},
    "delete_icon": {},
    "deleteButton": {},
    "DoneButton": {},
    "Dropdown1": {},
    "Dropdown2": {},
    "Dropdown3": {},
    "Edit_container": {},
    "EditSuccess_screen": {},
    "error_label": {},
    "ErrorMessage14_2": {},
    "ErrorMessage15_2": {},
    "ErrorMessage16_2": {},
    "ErrorMessage17_2": {},
    "ErrorMessage18_2": {},
    "ErrorMessage19_2": {},
    "ErrorMessage20_2": {},
    "ErrorMessage21_2": {},
    "ErrorMessage3_2": {},
    "ErrorMessage5_2": {},
    "eval1_label": {},
    "eval1_val": {},
    "eval2_label": {},
    "eval2_val": {},
    "eval3_label": {},
    "eval3_val": {},
    "eval4_label": {},
    "eval4_val": {},
    "eval5_label": {},
    "eval5_val": {},
    "eval6_label": {},
    "eval6_val": {},
    "evaluation_1_DataCard2_2": {},
    "evaluation_2_DataCard2_2": {},
    "evaluation_3_DataCard2_2": {},
    "evaluation_4_DataCard2_2": {},
    "evaluation_5_DataCard2_2": {},
    "evaluation_6_DataCard2_2": {},
    "feedback_DataCard2_2": {},
    "Form": {},
    "Form1": {},
    "gal_group": {},
    "Gallery2": {},
    "Gallery2_1": {},
    "Gallery4": {},
    "Gallery5": {},
    "galleryTemplate1": {},
    "galleryTemplate3": {},
    "galleryTemplate3_1": {},
    "galleryTemplate5": {},
    "galleryTemplate6": {},
    "grader_1": {},
    "grader_2": {},
    "grader_3": {},
    "grader_4": {},
    "grader_dropdown": {},
    "Grader_dropdown_2": {},
    "grader_label": {},
    "Grader_login_button": {},
    "Grader_MainContainer": {},
    "grader_val": {},
    "GraderCard_name": {},
    "Grading_screen": {},
    "GradingCertification_screen": {},
    "group_1": {},
    "group_dropdown": {},
    "Group_dropdown_1": {},
    "group_id_DataCard3_2": {},
    "group_label": {},
    "Group_MainContainer": {},
    "group_val": {},
    "Group4": {},
    "GroupCard_name": {},
    "gs_grader_label": {},
    "gs_group_label": {},
    "gs_infoDropdowns": {},
    "gs_infoLabels": {},
    "gs_venue_label": {},
    "Icon1": {},
    "Icon1_1": {},
    "Icon1_10": {},
    "Icon1_11": {},
    "Icon1_12": {},
    "Icon1_2": {},
    "Icon1_3": {},
    "Icon1_4": {},
    "Icon1_5": {},
    "Icon1_6": {},
    "Icon1_7": {},
    "Icon1_8": {},
    "Icon1_9": {},
    "Icon2": {},
    "Icon4": {},
    "Icon4_1": {},
    "Icon5": {},
    "Icon6": {},
    "Icon8": {},
    "iconCheck1": {},
    "iconCheck1_1": {},
    "iconCircle1": {},
    "iconCircle1_1": {},
    "lab_group": {},
    "Label1": {},
    "Label10": {},
    "Label10_1": {},
    "Label11": {},
    "Label11_1": {},
    "Label11_2": {},
    "Label11_3": {},
    "Label13": {},
    "Label14": {},
    "Label15": {},
    "Label2": {},
    "Label2_1": {},
    "Label2_2": {},
    "Label2_3": {},
    "Label2_4": {},
    "Label2_5": {},
    "Label3": {},
    "Label3_1": {},
    "Label3_2": {},
    "Label3_3": {},
    "Label3_4": {},
    "Label3_5": {},
    "Label3_6": {},
    "Label4": {},
    "Label5": {},
    "Label5_1": {},
    "Label6": {},
    "Label7": {},
    "Label8": {},
    "Label8_1": {},
    "Label9": {},
    "Label9_1": {},
    "LblSuccessMsg1": {},
    "LblSuccessMsg1_1": {},
    "List_gallery": {},
    "List_screen": {},
    "Login_screen": {},
    "Management_Screen": {},
    "Manager_login_button": {},
    "Modeselect_screen": {},
    "NewSuccess_screen": {},
    "next_arrow": {},
    "password_button": {},
    "password_group": {},
    "password_textInput": {},
    "Rectangle1": {},
    "Rectangle3": {},
    "Rectangle3_1": {},
    "Rectangle3_2": {},
    "Rectangle3_3": {},
    "Rectangle3_4": {},
    "Rectangle3_5": {},
    "Rectangle3_6": {},
    "Rectangle5": {},
    "Rectangle6": {},
    "Rectangle7": {},
    "Rectangle8": {},
    "room_dropdown": {},
    "room_label": {},
    "room_val": {},
    "ScoreSummaryTable": {},
    "SideBar_container": {},
    "Sort_dropdown_1": {},
    "Sort_dropdown_2": {},
    "StarVisible14_2": {},
    "StarVisible15_2": {},
    "StarVisible16_2": {},
    "StarVisible17_2": {},
    "StarVisible18_2": {},
    "StarVisible19_2": {},
    "StarVisible20_2": {},
    "StarVisible21_2": {},
    "StarVisible3_2": {},
    "StarVisible5_2": {},
    "tab_group": {},
    "tab_group_1": {},
    "tab_group_2": {},
    "tab_group_3": {},
    "tab_group_4": {},
    "tab_group_5": {},
    "tab_group_6": {},
    "Test_7F478737223C4B69": {},
    "TextInput10": {},
    "TextInput10_1": {},
    "toListScreen_button": {},
    "total_1": {},
    "total_2": {},
    "total_label": {},
    "total_val": {},
    "user_id_DataCard1_2": {},
    "vanue_label": {},
    "vanue_val": {},
    "Venue_dropdown_3": {},
    "Venue_dropdown_4": {},
    "venue_id_DataCard1_2": {}
  },
  "PCFDynamicSchemaForIRRetrievalEntry": {},
  "PublishOrderIndices": {
    "6f4a661c-b0b9-47c7-850e-056aa27a82ca": 163,
    "a99308fb-2b04-457c-bb7c-9f87f1f945b0": 162,
    "AddButton": 205,
    "App": 0,
    "Button2": 72,
    "Button3": 207,
    "Button4_1": 15,
    "Button4_2": 141,
    "Button4_3": 145,
    "Button4_4": 16,
    "cancelButton": 203,
    "Circle1": 204,
    "Component1": 1,
    "DataCardKey14_2": 135,
    "DataCardKey15_2": 95,
    "DataCardKey16_2": 110,
    "DataCardKey17_2": 115,
    "DataCardKey18_2": 120,
    "DataCardKey19_2": 125,
    "DataCardKey20_2": 130,
    "DataCardKey22_2": 90,
    "DataCardKey3_2": 100,
    "DataCardKey5_2": 105,
    "DataCardValue14_2": 136,
    "DataCardValue15_2": 96,
    "DataCardValue16_2": 111,
    "DataCardValue17_2": 116,
    "DataCardValue18_2": 121,
    "DataCardValue19_2": 126,
    "DataCardValue20_2": 131,
    "DataCardValue22_2": 91,
    "DataCardValue3_2": 101,
    "DataCardValue5_2": 106,
    "date_dropdown": 64,
    "date_label": 34,
    "date_val": 49,
    "del_v": 188,
    "delete_icon": 199,
    "deleteButton": 202,
    "DoneButton": 86,
    "Dropdown1": 80,
    "Dropdown2": 83,
    "Dropdown3": 85,
    "Edit_container": 167,
    "EditSuccess_screen": 80,
    "error_label": 71,
    "ErrorMessage14_2": 137,
    "ErrorMessage15_2": 97,
    "ErrorMessage16_2": 112,
    "ErrorMessage17_2": 117,
    "ErrorMessage18_2": 122,
    "ErrorMessage19_2": 127,
    "ErrorMessage20_2": 132,
    "ErrorMessage21_2": 92,
    "ErrorMessage3_2": 102,
    "ErrorMessage5_2": 107,
    "eval1_label": 36,
    "eval1_val": 51,
    "eval2_label": 37,
    "eval2_val": 52,
    "eval3_label": 38,
    "eval3_val": 53,
    "eval4_label": 39,
    "eval4_val": 54,
    "eval5_label": 40,
    "eval5_val": 55,
    "eval6_label": 41,
    "eval6_val": 56,
    "evaluation_1_DataCard2_2": 93,
    "evaluation_2_DataCard2_2": 108,
    "evaluation_3_DataCard2_2": 113,
    "evaluation_4_DataCard2_2": 118,
    "evaluation_5_DataCard2_2": 123,
    "evaluation_6_DataCard2_2": 128,
    "feedback_DataCard2_2": 133,
    "Form": 87,
    "Form1": 173,
    "gal_group": 46,
    "Gallery2": 190,
    "Gallery2_1": 195,
    "Gallery4": 0,
    "Gallery5": 0,
    "galleryTemplate1": 44,
    "galleryTemplate3": 191,
    "galleryTemplate3_1": 196,
    "galleryTemplate5": 0,
    "galleryTemplate6": 0,
    "grader_1": 149,
    "grader_2": 150,
    "grader_3": 150,
    "grader_4": 150,
    "grader_dropdown": 69,
    "Grader_dropdown_2": 26,
    "grader_label": 32,
    "Grader_login_button": 3,
    "Grader_MainContainer": 186,
    "grader_val": 47,
    "GraderCard_name": 177,
    "Grading_screen": 24,
    "GradingCertification_screen": 12,
    "group_1": 148,
    "group_dropdown": 67,
    "Group_dropdown_1": 25,
    "group_id_DataCard3_2": 88,
    "group_label": 30,
    "Group_MainContainer": 184,
    "group_val": 45,
    "Group4": 211,
    "GroupCard_name": 174,
    "gs_grader_label": 82,
    "gs_group_label": 78,
    "gs_infoDropdowns": 81,
    "gs_infoLabels": 79,
    "gs_venue_label": 84,
    "Icon1": 13,
    "Icon1_1": 77,
    "Icon1_10": 59,
    "Icon1_11": 75,
    "Icon1_12": 11,
    "Icon1_2": 210,
    "Icon1_3": 171,
    "Icon1_4": 61,
    "Icon1_5": 11,
    "Icon1_6": 21,
    "Icon1_7": 13,
    "Icon1_8": 169,
    "Icon1_9": 19,
    "Icon2": 194,
    "Icon4": 193,
    "Icon4_1": 198,
    "Icon5": 172,
    "Icon6": 200,
    "Icon8": 206,
    "iconCheck1": 139,
    "iconCheck1_1": 143,
    "iconCircle1": 138,
    "iconCircle1_1": 142,
    "lab_group": 31,
    "Label1": 208,
    "Label10": 183,
    "Label10_1": 185,
    "Label11": 63,
    "Label11_1": 65,
    "Label11_2": 68,
    "Label11_3": 70,
    "Label13": 168,
    "Label14": 201,
    "Label15": 0,
    "Label2": 0,
    "Label2_1": 0,
    "Label2_2": 0,
    "Label2_3": 0,
    "Label2_4": 0,
    "Label2_5": 0,
    "Label3": 12,
    "Label3_1": 2,
    "Label3_2": 20,
    "Label3_3": 60,
    "Label3_4": 76,
    "Label3_5": 170,
    "Label3_6": 12,
    "Label4": 209,
    "Label5": 192,
    "Label5_1": 197,
    "Label6": 23,
    "Label7": 24,
    "Label8": 182,
    "Label8_1": 189,
    "Label9": 175,
    "Label9_1": 178,
    "LblSuccessMsg1": 140,
    "LblSuccessMsg1_1": 144,
    "List_gallery": 43,
    "List_screen": 31,
    "Login_screen": 69,
    "Management_Screen": 0,
    "Manager_login_button": 8,
    "Modeselect_screen": 76,
    "NewSuccess_screen": 80,
    "next_arrow": 7,
    "password_button": 6,
    "password_group": 5,
    "password_textInput": 4,
    "Rectangle1": 22,
    "Rectangle3": 9,
    "Rectangle3_1": 0,
    "Rectangle3_2": 17,
    "Rectangle3_3": 58,
    "Rectangle3_4": 73,
    "Rectangle3_5": 163,
    "Rectangle3_6": 9,
    "Rectangle5": 180,
    "Rectangle6": 166,
    "Rectangle7": 165,
    "Rectangle8": 187,
    "room_dropdown": 66,
    "room_label": 35,
    "room_val": 50,
    "ScoreSummaryTable": 86,
    "SideBar_container": 181,
    "Sort_dropdown_1": 28,
    "Sort_dropdown_2": 29,
    "StarVisible14_2": 134,
    "StarVisible15_2": 94,
    "StarVisible16_2": 109,
    "StarVisible17_2": 114,
    "StarVisible18_2": 119,
    "StarVisible19_2": 124,
    "StarVisible20_2": 129,
    "StarVisible21_2": 89,
    "StarVisible3_2": 99,
    "StarVisible5_2": 104,
    "tab_group": 10,
    "tab_group_1": 1,
    "tab_group_2": 18,
    "tab_group_3": 62,
    "tab_group_4": 74,
    "tab_group_5": 164,
    "tab_group_6": 10,
    "Test_7F478737223C4B69": 0,
    "TextInput10": 176,
    "TextInput10_1": 179,
    "toListScreen_button": 14,
    "total_1": 151,
    "total_2": 152,
    "total_label": 42,
    "total_val": 57,
    "user_id_DataCard1_2": 98,
    "vanue_label": 33,
    "vanue_val": 48,
    "Venue_dropdown_3": 27,
    "Venue_dropdown_4": 27,
    "venue_id_DataCard1_2": 103
  },
  "ResourcesJsonIndices": {
    "Image-SampleImage": 0
  },
  "RuleScreenIdWithoutScreen": {},
  "TemplateVersions": {},
  "VolatileProperties": {
    "AnalysisLoadTime": 2.1725901,
    "ControlCount": {
      "b865ef078df94062b671e7e610e0cb05": 1,
      "button": 13,
      "circle": 3,
      "dropdown": 19,
      "form": 2,
      "gallery": 5,
      "galleryTemplate": 5,
      "group": 20,
      "icon": 27,
      "label": 101,
      "rectangle": 13,
      "screen": 9,
      "TestCase": 1,
      "TestSuite": 1,
      "text": 7,
      "typedDataCard": 12
    },
    "DeserializationLoadTime": 8.4761479,
    "ErrorCount": 2
  },
  "WasLocalDatabaseReferencesEmpty": true
}